{
    "display": {
        "icon": {
            "item": "minecraft:diamond_pickaxe",
			"nbt": "{Unbreakable:1b,Damage:5,CustomModelData:26}"
        },
        "title": {
            "type": "translatable", "translate": "luigis_mansion:advancements.vanilla.to_infinity_and_beyond"
        },
        "description": {
            "type": "translatable", "translate": "luigis_mansion:advancements.vanilla.to_infinity_and_beyond.description"
        },
        "hidden": true
    },
	"parent": "luigis_mansion:vanilla/root",
    "criteria": {
        "scan_moon": {
            "trigger": "minecraft:impossible"
        }
    },
	"rewards": {
		"function": "luigis_mansion:advancements/vanilla/to_infinity_and_beyond"
	}
}