{
    "display": {
        "icon": {
            "item": "minecraft:leather_chestplate",
			"nbt": "{Unbreakable:1b,Damage:4,CustomModelData:0,display:{color:16768768}}"
        },
        "show_toast": false,
        "announce_to_chat": false,
        "title": {
            "translate": "luigis_mansion:entity.yellow_bat"
        },
        "description": {
            "translate": "luigis_mansion:advancements.vanilla.waluigi_pinball.sub_description"
        }
    },
	"parent": "luigis_mansion:vanilla/waluigi_pinball/purple_bat",
    "criteria": {
        "bumped_into": {
            "trigger": "minecraft:impossible"
        }
    },
	"rewards": {
		"function": "luigis_mansion:advancements/vanilla/waluigi_pinball/yellow_bat"
	}
}