{
    "display": {
        "icon": {
            "count": 1,
            "id": "minecraft:diamond_pickaxe",
            "components": {
                "minecraft:unbreakable": {},
                "minecraft:damage": 1,
                "minecraft:custom_model_data": 20
            }
        },
        "show_toast": false,
        "announce_to_chat": false,
        "title": {
            "type": "translatable", "translate": "luigis_mansion:entity.shivers"
        },
        "description": {
            "type": "translatable", "translate": "luigis_mansion:advancements.vanilla.waluigi_pinball.sub_description"
        }
    },
	"parent": "luigis_mansion:vanilla/waluigi_pinball/floating_whirlindas",
    "criteria": {
        "bumped_into": {
            "trigger": "minecraft:impossible"
        }
    },
	"rewards": {
		"function": "luigis_mansion:advancements/vanilla/waluigi_pinball/shivers"
	}
}