{
    "parent": "luigis_mansion:entity/billiards_ball/yellow",
    "overrides": [
        {
            "predicate": {
                "custom_model_data": 0
            },
            "model": "luigis_mansion:entity/billiards_ball/yellow"
        },
        {
            "predicate": {
                "custom_model_data": 1
            },
            "model": "luigis_mansion:entity/billiards_ball/red"
        },
        {
            "predicate": {
                "custom_model_data": 2
            },
            "model": "luigis_mansion:entity/billiards_ball/purple"
        },
        {
            "predicate": {
                "custom_model_data": 3
            },
            "model": "luigis_mansion:entity/billiards_ball/white"
        }
    ]
}