{
    "parent": "luigis_mansion:entity/heart/ghost",
    "overrides": [
        {
            "predicate": {
                "custom_model_data": 0
            },
            "model": "luigis_mansion:entity/heart/ghost"
        },
        {
            "predicate": {
                "custom_model_data": 1
            },
            "model": "luigis_mansion:entity/heart/burning"
        },
        {
            "predicate": {
                "custom_model_data": 2
            },
            "model": "luigis_mansion:entity/heart/watery"
        },
        {
            "predicate": {
                "custom_model_data": 3
            },
            "model": "luigis_mansion:entity/heart/frozen"
        }
    ]
}